Metadata-Version: 1.0
Name: bi-dist
Version: 0.1
Summary: Gaussian distributions
Home-page: UNKNOWN
Author: jennifer chukwu
Author-email: jnyfaah@gmaail.com
License: UNKNOWN
Platform: UNKNOWN
